[{"Id":0,"NumeroCarte":"4974018502234567","Montant":340,"TypeOperation":"Retrait DAB","DateOperation":"2018-05-08T12:23:27","Devise":"GBP","TauxDeChange":0},{"Id":0,"NumeroCarte":"4974018502238951","Montant":219,"TypeOperation":"Facture CB","DateOperation":"2020-06-12T16:11:54","Devise":"CAD","TauxDeChange":0},{"Id":0,"NumeroCarte":"4974018502233824","Montant":61,"TypeOperation":"Depot Guichet","DateOperation":"2020-04-20T13:26:25","Devise":"JPY","TauxDeChange":0},{"Id":0,"NumeroCarte":"4974018502235738","Montant":222,"TypeOperation":"Retrait DAB","DateOperation":"2021-07-16T12:57:36","Devise":"AUD","TauxDeChange":0},{"Id":0,"NumeroCarte":"4974018502234012","Montant":238,"TypeOperation":"Depot Guichet","DateOperation":"2019-06-06T05:39:59","Devise":"EUR","TauxDeChange":0},{"Id":0,"NumeroCarte":"4974018502237456","Montant":241,"TypeOperation":"Facture CB","DateOperation":"2020-05-25T01:48:56","Devise":"EUR","TauxDeChange":0},{"Id":0,"NumeroCarte":"4974018502239463","Montant":283,"TypeOperation":"Retrait DAB","DateOperation":"2022-03-27T20:37:59","Devise":"CHF","TauxDeChange":0},{"Id":0,"NumeroCarte":"4974018502231230","Montant":312,"TypeOperation":"Facture CB","DateOperation":"2020-11-20T11:58:22","Devise":"USD","TauxDeChange":0},{"Id":0,"NumeroCarte":"4974018502232569","Montant":301,"TypeOperation":"Depot Guichet","DateOperation":"2021-07-31T14:57:01","Devise":"JPY","TauxDeChange":0},{"Id":0,"NumeroCarte":"4974018502237654","Montant":446,"TypeOperation":"Retrait DAB","DateOperation":"2021-03-16T01:15:08","Devise":"GBP","TauxDeChange":0},{"Id":0,"NumeroCarte":"4974018502231347","Montant":220,"TypeOperation":"Facture CB","DateOperation":"2020-08-16T04:44:53","Devise":"CHF","TauxDeChange":0},{"Id":0,"NumeroCarte":"4974018502235941","Montant":80,"TypeOperation":"Depot Guichet","DateOperation":"2018-03-16T03:55:30","Devise":"GBP","TauxDeChange":0},{"Id":0,"NumeroCarte":"4974018502238713","Montant":439,"TypeOperation":"Retrait DAB","DateOperation":"2020-02-11T14:51:27","Devise":"AUD","TauxDeChange":0},{"Id":0,"NumeroCarte":"4974018502232698","Montant":187,"TypeOperation":"Depot Guichet","DateOperation":"2019-03-24T13:56:18","Devise":"CAD","TauxDeChange":0},{"Id":0,"NumeroCarte":"4974018502238452","Montant":158,"TypeOperation":"Retrait DAB","DateOperation":"2018-04-27T19:55:01","Devise":"JPY","TauxDeChange":0},{"Id":0,"NumeroCarte":"4974018502233092","Montant":323,"TypeOperation":"Facture CB","DateOperation":"2021-11-13T15:46:03","Devise":"EUR","TauxDeChange":0},{"Id":0,"NumeroCarte":"4974018502234530","Montant":444,"TypeOperation":"Retrait DAB","DateOperation":"2019-08-24T10:14:22","Devise":"EUR","TauxDeChange":0},{"Id":0,"NumeroCarte":"4974018502237620","Montant":281,"TypeOperation":"Depot Guichet","DateOperation":"2018-02-19T07:00:21","Devise":"EUR","TauxDeChange":0},{"Id":0,"NumeroCarte":"4974018502236394","Montant":481,"TypeOperation":"Retrait DAB","DateOperation":"2018-12-01T06:32:03","Devise":"AUD","TauxDeChange":0},{"Id":0,"NumeroCarte":"4974018502231264","Montant":129,"TypeOperation":"Facture CB","DateOperation":"2018-09-15T01:57:20","Devise":"JPY","TauxDeChange":0}]